{"name":"RedHat Cluster Agents","tagline":"RedHat cluster agents and scripts","body":"## PostgreSQL resource agents\r\n\r\nFull PostgreSQL support, including replication and transaction logs shipping. Maximal splitbrain protection.\r\n\r\nFor usage see examples in `config/` directory.\r\n\r\n### PostgreSQL service agent (postgres)\r\nControls PostgreSQL service state and parameters.\r\n\r\n### PostgreSQL Master resource agent (postgres_masterslave)\r\nControls PostgreSQL master role over cluster.\r\n\r\n### PostgreSQL WAL receiver agent (pg_receivexlog)\r\nControls WAL receiver process with all its parameters. In fact, it's just an init-script replacement.","google":"","note":"Don't delete this file! It's used internally to help with page regeneration."}